react_render/__init__.py
react_render/core.py
react_render/exceptions.py
react_render/render.py
react_render/django/__init__.py
react_render/django/models.py
react_render/django/render.py
tests/test_app/__init__.py
tests/test_app/models.py
react_render_client-1.3.2.dist-info/LICENSE.txt
react_render_client-1.3.2.dist-info/METADATA
react_render_client-1.3.2.dist-info/WHEEL
react_render_client-1.3.2.dist-info/top_level.txt
react_render_client-1.3.2.dist-info/RECORD
